{
  "meta": {
    "updated_iso": "2026-07-14T17:19:03.620377+07:00",
    "updated_date": "2026-07-14",
    "updated_th": "14 ก.ค. 2569 เวลา 17:19 น.",
    "gta_round": "4",
    "gta_time_th": "14/07/2569 เวลา 09:59 น.",
    "source_thai": "stale",
    "source_spot": "gold-api.com",
    "notes": "14 Jul (Tue): GTA classic posted fresh round-4 price at 09:59 Bangkok (63,700/63,500), first live update since Saturday 11/07 -- ends the multi-day stale streak. Bar sell down THB1,300 (-2.0%) vs the carried-over Saturday price. Spot XAU/USD (gold-api.com) at $4,059.90 (-1.3% vs prior read) and USD/THB (er-api.com) roughly flat at 33.34.",
    "analysis_updated_th": "14 ก.ค. 2569 เวลา 10:50 น."
  },
  "thai_gold": {
    "bar_sell": 63700,
    "bar_buy": 63500,
    "jewelry_sell": 64500,
    "jewelry_buy": 62231.8,
    "bar_sell_prev": 65000,
    "bar_buy_prev": 64800
  },
  "spot": {
    "xau_usd": 4020.3,
    "xau_usd_prev": 4065.3,
    "usd_thb": 33.436,
    "usd_thb_prev": 33.3402,
    "london_am": 4070.95,
    "london_pm": 4039.75,
    "newyork": 4016.44
  },
  "monthly_bar_sell": [
    {
      "label": "ก.พ.",
      "year": 2569,
      "price": 70500
    },
    {
      "label": "มี.ค.",
      "year": 2569,
      "price": 67800
    },
    {
      "label": "เม.ย.",
      "year": 2569,
      "price": 68050
    },
    {
      "label": "พ.ค.",
      "year": 2569,
      "price": 66050
    },
    {
      "label": "มิ.ย.",
      "year": 2569,
      "price": 65600
    },
    {
      "label": "ก.ค.",
      "year": 2569,
      "price": 63700,
      "current": true
    }
  ],
  "spot_history": [
    {
      "date": "2026-07-02",
      "xau": 4090.0,
      "thb": 33.05,
      "bar_sell": 64650
    },
    {
      "date": "2026-07-03",
      "xau": 4148.0,
      "thb": 33.1,
      "bar_sell": 66050
    },
    {
      "date": "2026-07-06",
      "xau": 4139.0,
      "thb": 33.18,
      "bar_sell": 65750
    },
    {
      "date": "2026-07-07",
      "xau": 4142.0,
      "thb": 33.22,
      "bar_sell": 65250
    },
    {
      "date": "2026-07-08",
      "xau": 4127.4,
      "thb": 33.31,
      "bar_sell": 65100
    },
    {
      "date": "2026-07-09",
      "xau": 4090.1,
      "thb": 33.4676,
      "bar_sell": 65050
    },
    {
      "date": "2026-07-10",
      "xau": 4106.8,
      "thb": 33.414,
      "bar_sell": 65000
    },
    {
      "date": "2026-07-11",
      "xau": 4121.4,
      "thb": 33.3051,
      "bar_sell": 64800
    },
    {
      "date": "2026-07-12",
      "xau": 4121.4,
      "thb": 33.309,
      "bar_sell": 65000
    },
    {
      "date": "2026-07-13",
      "xau": 4065.3,
      "thb": 33.3402,
      "bar_sell": 65000
    },
    {
      "date": "2026-07-14",
      "xau": 4020.3,
      "thb": 33.436,
      "bar_sell": 63700
    }
  ],
  "analysis": {
    "as_of": "14 ก.ค. 2569",
    "highlights": [
      {
        "icon": "🇹🇭",
        "color": "red",
        "tag": "ทองไทยแท่ง 96.5% ร่วง ฿1,300 สู่ ฿63,700 — สมาคมฯ ประกาศราคาสดครั้งแรกในรอบหลายวัน (รอบ 4, 09:59 น.)",
        "sub": "ลดจาก ฿65,000 ที่ค้างมาตั้งแต่เสาร์ ตามทองโลกที่อ่อนตัว · ทองรูปพรรณขายออก ฿64,500"
      },
      {
        "icon": "📉",
        "color": "red",
        "tag": "Fed Waller เตือนอาจต้องขึ้นดอกเบี้ย 'ในระยะใกล้' หากเงินเฟ้อยังร้อน — ทองร่วงหลุด $4,000 เมื่อ 13 ก.ค.",
        "sub": "XAU/USD ดิ่งเกือบ 3% ปิดที่ $4,001.40 ทดสอบแนวรับปีที่ ~$3,900 · ตลาดเพิ่มโอกาสขึ้นดอกเบี้ย ก.ค. เป็น ~40%"
      },
      {
        "icon": "📊",
        "color": "yellow",
        "tag": "จับตา CPI สหรัฐ มิ.ย. คืนนี้ 14 ก.ค. (19:30 น.ไทย) ตลาดคาดชะลอลงเหลือ ~3.9% YoY จาก 4.2%",
        "sub": "Core CPI คาด ~2.9% · ราคาน้ำมันที่ย่อลงหลังสถานการณ์อิหร่านคลี่คลายบางส่วนช่วยลดแรงกดเงินเฟ้อ"
      },
      {
        "icon": "🏛️",
        "color": "blue",
        "tag": "Kevin Warsh แถลงนโยบายต่อสภาผู้แทนฯ วันนี้ ห่างจาก CPI เพียง 90 นาที ต่อด้วยวุฒิสภาพรุ่งนี้ 15 ก.ค.",
        "sub": "รายงานฉบับแรกภายใต้ Warsh ชูแนวคิด monetarism · ตลาดจับตาสัญญาณต่อการขึ้นดอกเบี้ย ก.ค.-ก.ย."
      },
      {
        "icon": "🐉",
        "color": "purple",
        "tag": "PBOC ซื้อทองต่อเนื่องเดือนที่ 20 — 14.93 ตันใน มิ.ย. มากสุดตั้งแต่ปี 2023",
        "sub": "สำรองรวม 75.44 ล้านออนซ์ (~2,346 ตัน) ยังไม่ถึง 10% ของทุนสำรอง · ยังไม่มีตัวเลข ก.ค. อย่างเป็นทางการ"
      },
      {
        "icon": "🎯",
        "color": "gold",
        "tag": "ธนาคารใหญ่ทยอยหั่นคาดการณ์ทอง 2026 — HSBC เหลือ $4,560 เฉลี่ย, BofA ลด 14% เหลือ $4,360",
        "sub": "ทั้งคู่คงเป้าระยะยาว/สิ้นปีไว้ (HSBC $4,750, BofA $6,000 หลังวงจรขึ้นดอกเบี้ยจบ) อ้างเฟดฮอว์กิชกดราคา"
      }
    ],
    "geopolitics": {
      "title": "สงบศึกอิหร่าน-สหรัฐฯ ยังไม่คลี่คลายเต็มที่ แต่ราคาน้ำมันเริ่มย่อตัวจากจุดสูงสุด",
      "text": "หลังทรัมป์ประกาศเมื่อ 8 ก.ค. ว่าข้อตกลงสงบศึกกับอิหร่าน \"จบแล้ว\" และสหรัฐฯ ถล่มกว่า 80 เป้าหมายทางทหารอิหร่าน ขณะที่อิหร่านตอบโต้ฐานทัพสหรัฐฯ ในบาห์เรน-คูเวต สถานการณ์ในช่องแคบฮอร์มุซยังคงตึงเครียดและยังไม่มีข้อตกลงใหม่ที่ยืนยันได้ อย่างไรก็ตาม ราคาน้ำมันเบรนท์ที่เคยพุ่งใกล้ $80 ได้ย่อตัวลงบางส่วนในช่วงปลายเดือนมิ.ย.-ต้นก.ค. ซึ่งเป็นหนึ่งในเหตุผลที่ตลาดคาดว่า CPI เดือนมิ.ย. ของสหรัฐฯ จะชะลอตัวลงเหลือราว 3.9% จาก 4.2% ในเดือนพ.ค. แม้ความเสี่ยงภูมิรัฐศาสตร์จะยังไม่คลี่คลาย แต่ทองคำกลับไม่ได้แรงหนุน Safe Haven เต็มที่ เพราะตลาดให้น้ำหนักกับสัญญาณเฟดฮอว์กิชและดอลลาร์แข็งค่ามากกว่า ส่งผลให้ราคาทองร่วงหลุด $4,000 เมื่อ 13 ก.ค. ก่อนจะทรงตัวแถว $4,050-4,060 ในช่วงเช้าวันนี้"
    },
    "fed": {
      "title": "Waller เตือนอาจต้องขึ้นดอกเบี้ย — CPI และ Warsh แถลงต่อสภาคองเกรสวันนี้คือตัวชี้ขาด",
      "text": "Fed Governor <b>Christopher Waller</b> กล่าวเมื่อ 13 ก.ค. ว่าเฟดอาจจำเป็นต้องขึ้นดอกเบี้ย <b>\"ในระยะใกล้\"</b> หากข้อมูลเงินเฟ้อที่จะออกมายังคงร้อนแรงเหนือเป้าหมาย 2% อย่างต่อเนื่อง คำเตือนนี้ฉุดราคาทองร่วงหลุด <b>$4,000</b> ทันที (-2.9% ในวันเดียว) และดันดัชนีดอลลาร์แข็งค่าขึ้น ตลาดปรับเพิ่มโอกาสขึ้นดอกเบี้ยในการประชุม <b>28-29 ก.ค.</b> เป็นราว <b>40%</b> (จากใกล้ 0% ก่อนหน้า) และให้น้ำหนักขึ้นดอกเบี้ยเดือน <b>ก.ย.</b> รวมกันราว <b>58%</b> (25bps ~47% + 50bps ~11%) สอดคล้องกับ Minutes มิ.ย. ที่ชี้คณะกรรมการแตกเสียง 9 ขึ้น/8 คง ตัวชี้ขาดของสัปดาห์นี้คือ <b>CPI เดือน มิ.ย.</b> ประกาศคืนนี้ <b>14 ก.ค. เวลา 19:30 น. ไทย</b> ตลาดคาดชะลอลงเหลือ <b>~3.9% YoY</b> จาก 4.2% ในพ.ค. (Core คาด ~2.9%) ตามด้วยประธาน Fed <b>Kevin Warsh</b> แถลงนโยบายการเงินรอบครึ่งปีต่อสภาผู้แทนราษฎรในวันเดียวกัน ห่างจากตัวเลข CPI เพียง 90 นาที และต่อวุฒิสภาวันพุธที่ <b>15 ก.ค.</b> — หาก CPI ออกมาร้อนแรงกว่าคาดพร้อมโทน Warsh ที่ hawkish ราคาทองมีโอกาสถูกกดดันต่อ แต่หากเย็นกว่าคาดตามที่ตลาดคาดการณ์ไว้ อาจเห็นแรงซื้อคืนบางส่วน"
    },
    "central_banks": "<b>PBOC จีน</b> ซื้อทองต่อเนื่องเดือนที่ 20 — เพิ่ม <b>14.93 ตัน</b> (480,000 ออนซ์) ใน มิ.ย. มากสุดนับตั้งแต่ปี 2023 สำรองรวม <b>75.44 ล้านออนซ์ (~2,346 ตัน)</b> ยังไม่ถึง 10% ของทุนสำรองทั้งหมด (เทียบสหรัฐฯ ที่ราว 70%) ยังไม่มีตัวเลขซื้อ ก.ค. อย่างเป็นทางการ · นักวิเคราะห์มองการซื้อสวนทางช่วงราคาอ่อนตัวเป็นกลยุทธ์ counter-cyclical ของจีนเพื่อลดพึ่งพาสินทรัพย์ดอลลาร์ · <b>WGC</b> ประเมินการซื้อจริง (รวมไม่รายงาน) Q1/2026 ที่ <b>244 ตัน</b> สูงกว่า Q4/2025 (208 ตัน) · UBS มองธนาคารกลางทั่วโลกจะซื้อทองต่อเนื่องปีนี้ในช่วง <b>750–1,000 ตัน</b> หนุนตลาดกระทิงเชิงโครงสร้างที่ยังไม่เปลี่ยนทิศ",
    "sentiment": {
      "bull": 42,
      "neutral": 30,
      "bear": 28
    },
    "forecasts": [
      {
        "house": "J.P. Morgan",
        "target": "$6,000",
        "horizon": "เฉลี่ย Q4/2026 (คงเป้า 9 มิ.ย.)"
      },
      {
        "house": "HSBC",
        "target": "$4,560",
        "horizon": "เฉลี่ยปี 2026 (ลดจาก $4,864 · 9 ก.ค.) — คงเป้าสิ้นปีที่ $4,750 ในกรอบ $3,800–4,700"
      },
      {
        "house": "Bank of America",
        "target": "$4,360",
        "horizon": "เฉลี่ยปี 2026 (ลด 14% จาก $5,093 · 8 ก.ค.) — คงเป้าระยะยาว $6,000 หลังวงจรขึ้นดอกเบี้ยจบ"
      },
      {
        "house": "Morgan Stanley",
        "target": "$5,700",
        "horizon": "สิ้นปี 2026"
      },
      {
        "house": "UBS",
        "target": "$5,500",
        "horizon": "สิ้นปี 2026 (ลดจาก $5,900) · คาดธนาคารกลางซื้อ 750–1,000 ตัน/ปี"
      },
      {
        "house": "Goldman Sachs",
        "target": "$4,900",
        "horizon": "สิ้นปี 2026 (ลดจาก $5,400 · 20 มิ.ย.) · $4,400 หาก Fed ขึ้นดอกเบี้ยจริง"
      },
      {
        "house": "Metals Focus",
        "target": "$4,920",
        "horizon": "สิ้นปี 2026"
      }
    ],
    "catalysts": [
      {
        "color": "yellow",
        "tag": "ข้อมูล",
        "text": "CPI สหรัฐเดือน มิ.ย. ประกาศคืนนี้ 14 ก.ค. (19:30 น. ไทย) — ตลาดคาดชะลอเหลือ 3.9% YoY จาก 4.2%"
      },
      {
        "color": "blue",
        "tag": "Fed",
        "text": "Kevin Warsh แถลงนโยบายการเงินต่อสภาผู้แทนฯ วันนี้ 14 ก.ค. (90 นาทีหลัง CPI) และวุฒิสภา 15 ก.ค."
      },
      {
        "color": "red",
        "tag": "Fed",
        "text": "Waller เตือนอาจต้องขึ้นดอกเบี้ย 'ในระยะใกล้' หากเงินเฟ้อยังร้อน — ตลาดเพิ่มโอกาสขึ้นดอกเบี้ย ก.ค. เป็น ~40%"
      },
      {
        "color": "purple",
        "tag": "ภูมิรัฐศาสตร์",
        "text": "สหรัฐฯ–อิหร่านยังตึงเครียดในฮอร์มุซ แม้น้ำมันเริ่มย่อตัวจากจุดสูงสุดหลังสงบศึกล่ม"
      },
      {
        "color": "green",
        "tag": "ค่าเงิน",
        "text": "ทิศทางบาท (~33.34/ดอลลาร์) และดอลลาร์สหรัฐที่แข็งค่าจากคาดการณ์ขึ้นดอกเบี้ยยังกดราคาทองบาท"
      }
    ],
    "news": [
      {
        "date": "14 ก.ค. 2569",
        "color": "gold",
        "tag": "ราคาไทย",
        "text": "ทองไทยแท่ง 96.5% ปรับลด ฿1,300 สู่ ฿63,700 — สมาคมฯ ประกาศราคาสดครั้งแรกในรอบหลายวัน (รอบ 4, 09:59 น.)"
      },
      {
        "date": "13 ก.ค. 2569",
        "color": "red",
        "tag": "Fed",
        "text": "Fed Waller เตือนอาจต้องขึ้นดอกเบี้ย 'ในระยะใกล้' หากเงินเฟ้อยังร้อนแรง — ทองร่วงหลุด $4,000"
      },
      {
        "date": "13 ก.ค. 2569",
        "color": "red",
        "tag": "ทองโลก",
        "text": "ราคาทองปิดที่ $4,001.40 ลดลง 2.90% ในวันเดียว จากแรงกดดันเฟดฮอว์กิชและดอลลาร์แข็งค่า"
      },
      {
        "date": "14 ก.ค. 2569",
        "color": "yellow",
        "tag": "ข้อมูล",
        "text": "จับตา CPI สหรัฐเดือน มิ.ย. คืนนี้ ตลาดคาดชะลอเหลือ 3.9% YoY จาก 4.2% หลังราคาน้ำมันย่อตัว"
      },
      {
        "date": "9 ก.ค. 2569",
        "color": "yellow",
        "tag": "สถาบัน",
        "text": "HSBC ปรับลดคาดการณ์ราคาทองเฉลี่ยปี 2026 เหลือ $4,560 จาก $4,864 แต่คงเป้าสิ้นปีที่ $4,750"
      },
      {
        "date": "7 ก.ค. 2569",
        "color": "purple",
        "tag": "ธนาคารกลาง",
        "text": "PBOC ซื้อทองเดือนที่ 20 ติดต่อกัน — 14.93 ตันใน มิ.ย. มากสุดตั้งแต่ปี 2023 สำรอง ~2,346 ตัน"
      }
    ]
  },
  "volatility": {
    "sd_pct": 2.7,
    "mean": 67600,
    "lo": 64130,
    "hi": 71070,
    "level": "ต่ำ (Low)",
    "vs_norm": -0.3,
    "closed": [
      70500,
      67800,
      68050,
      66050,
      65600
    ]
  },
  "odds": {
    "up": 33,
    "side": 22,
    "down": 45,
    "summary": "สัญญาณ 7 วันเอียงลง — แรงกดดันจากค่าเงินบาท/ทองโลกอ่อนตัว",
    "signals": [
      [
        "บาทอ่อนค่า หนุนทองบาท",
        "green"
      ],
      [
        "ทองโลกลงรายวัน",
        "red"
      ],
      [
        "หลุดค่าเฉลี่ย 5 วัน",
        "red"
      ],
      [
        "โมเมนตัมรายสัปดาห์ลบ",
        "red"
      ]
    ]
  },
  "tech": {
    "r2": 4200,
    "r1": 4050,
    "s1": 4000,
    "s2": 3975,
    "range_lo": 4020,
    "range_hi": 4148
  }
}